pycgms/Wofost71_PP.conf
pycgms/Wofost71_WLP_FD.conf
pycgms/__init__.py
pycgms/data_providers.py
pycgms/runner.py
pycgms-0.1.0.dist-info/entry_points.txt
pycgms-0.1.0.dist-info/WHEEL
pycgms-0.1.0.dist-info/METADATA
pycgms-0.1.0.dist-info/RECORD
