Metadata-Version: 2.1
Name: pycgms
Version: 0.1.0
Summary: The PyCGMS package provides a python implementation of the crop simulation
Home-page: https://github.com/ajwdewit/pyCGMS
License: UNKNOWN
Author: Allard de Wit
Author-email: allard.dewit@wur.nl
Classifier: Development Status :: 3 - Alpha
Classifier: Intended Audience :: Developers
Classifier: License :: OSI Approved :: European Union Public Licence 1.2 (EUPL 1.2)
Classifier: Programming Language :: Python :: 3
Requires-Dist: pcse >=5.4
Provides-Extra: .none
